{
  "name": "HHSelectPhoto",
  "version": "0.3.4",
  "summary": "A short description of HHSelectPhoto.",
  "description": "TODO: Add long description of the pod here.",
  "homepage": "https://github.com/michaelssman/HHSelectPhoto",
  "license": {
    "type": "MIT",
    "file": "LICENSE"
  },
  "authors": {
    "michaelstrongself@outlook.com": "michaelstrongself@outlook.com"
  },
  "source": {
    "git": "https://github.com/michaelssman/HHSelectPhoto.git",
    "tag": "0.3.4"
  },
  "platforms": {
    "ios": "10.0"
  },
  "source_files": "HHSelectPhoto/Classes/**/*",
  "resource_bundles": {
    "HHSelectPhoto": [
      "HHSelectPhoto/Assets/*.{png,jpeg,jpg,imageset}"
    ]
  },
  "dependencies": {
    "HHUtils": [

    ]
  }
}
